fabrial/__init__.py
fabrial/__main__.py
fabrial/main_window.py
fabrial/plotting.py
fabrial/secondary_window.py
fabrial/assets/icons/oven_icon.ico
fabrial/assets/icons/oven_icon.png
fabrial/assets/icons/internal/category.png
fabrial/assets/icons/internal/chart-up.png
fabrial/assets/icons/internal/chart.png
fabrial/assets/icons/internal/folder--arrow.png
fabrial/assets/icons/internal/folder-export.png
fabrial/assets/icons/internal/folder-horizontal-open.png
fabrial/assets/icons/internal/folder-horizontal.png
fabrial/assets/icons/internal/lightning.png
fabrial/assets/icons/internal/script-block.png
fabrial/assets/icons/internal/script-export.png
fabrial/assets/icons/internal/script-import.png
fabrial/classes/__init__.py
fabrial/classes/actions.py
fabrial/classes/exceptions.py
fabrial/classes/lock.py
fabrial/classes/metaclasses.py
fabrial/classes/sequence_runner.py
fabrial/classes/sequence_step.py
fabrial/classes/sequence_thread.py
fabrial/classes/step_runner.py
fabrial/classes/timer.py
fabrial/constants/__init__.py
fabrial/constants/entry_points.py
fabrial/constants/name.py
fabrial/constants/sequence.py
fabrial/constants/sequence_builder.py
fabrial/constants/paths/__init__.py
fabrial/constants/paths/base.py
fabrial/constants/paths/descriptions.py
fabrial/constants/paths/icons.py
fabrial/constants/paths/settings/__init__.py
fabrial/constants/paths/settings/plugins.py
fabrial/constants/paths/settings/saved_data.py
fabrial/constants/paths/settings/sequence.py
fabrial/custom_widgets/__init__.py
fabrial/custom_widgets/container.py
fabrial/custom_widgets/markdown_view.py
fabrial/custom_widgets/parameter_description.py
fabrial/custom_widgets/plot.py
fabrial/custom_widgets/ports_combo_box.py
fabrial/custom_widgets/augmented/__init__.py
fabrial/custom_widgets/augmented/button.py
fabrial/custom_widgets/augmented/dialog.py
fabrial/custom_widgets/augmented/groupbox.py
fabrial/custom_widgets/augmented/label.py
fabrial/custom_widgets/augmented/spin_box.py
fabrial-0.2.7.dist-info/METADATA
fabrial-0.2.7.dist-info/WHEEL
fabrial-0.2.7.dist-info/entry_points.txt
fabrial-0.2.7.dist-info/licenses/LICENSE
fabrial-0.2.7.dist-info/RECORD
