Metadata-Version: 2.4
Name: fabrial
Version: 0.2.7
Summary: Fabrial lets you create sequences to automate lab experiments.
Project-URL: Repository, https://github.com/Maughan-Lab/fabrial
Author-email: Drew Whitney <drewlwhitney@gmail.com>
Maintainer-email: Drew Whitney <drewlwhitney@gmail.com>
License-File: LICENSE
Requires-Python: >=3.13
Requires-Dist: fabrial-core-plugins
Requires-Dist: jinja2>=3.1.6
Requires-Dist: pyqt6>=6.9.1
Requires-Dist: pyqtgraph>=0.13.7
Requires-Dist: tendo>=0.3.0
Provides-Extra: shortcut
Requires-Dist: pyshortcuts; extra == 'shortcut'
